{
  "main": {
    "id": "b87faf38572f16c8",
    "type": "split",
    "children": [
      {
        "id": "b293b3b230365752",
        "type": "tabs",
        "children": [
          {
            "id": "ee2d0ef6c871c4fc",
            "type": "leaf",
            "state": {
              "type": "markdown",
              "state": {
                "file": "mock 数据接口相关.md",
                "mode": "source",
                "source": false
              }
            }
          },
          {
            "id": "cce6c4baa23671cc",
            "type": "leaf",
            "state": {
              "type": "markdown",
              "state": {
                "file": "typescript/Typescript 类型编程，从入门到念头通达.md",
                "mode": "source",
                "source": false
              }
            }
          },
          {
            "id": "e2259b049bf3e08d",
            "type": "leaf",
            "state": {
              "type": "markdown",
              "state": {
                "file": "vue3/admin.md",
                "mode": "source",
                "source": false
              }
            }
          },
          {
            "id": "f42ede68a0061097",
            "type": "leaf",
            "state": {
              "type": "markdown",
              "state": {
                "file": "组件问题/我的NPM最佳实践.md",
                "mode": "source",
                "source": false
              }
            }
          }
        ],
        "currentTab": 1
      }
    ],
    "direction": "vertical"
  },
  "left": {
    "id": "3360f029ca1370e6",
    "type": "split",
    "children": [
      {
        "id": "036881df21cf31c4",
        "type": "tabs",
        "children": [
          {
            "id": "42d03b7013090d6f",
            "type": "leaf",
            "state": {
              "type": "file-explorer",
              "state": {
                "sortOrder": "alphabetical"
              }
            }
          },
          {
            "id": "12495da245cbde8b",
            "type": "leaf",
            "state": {
              "type": "search",
              "state": {
                "query": "admin",
                "matchingCase": false,
                "explainSearch": false,
                "collapseAll": false,
                "extraContext": false,
                "sortOrder": "alphabetical"
              }
            }
          }
        ]
      }
    ],
    "direction": "horizontal",
    "width": 384
  },
  "right": {
    "id": "19e24e2ffe79f6a6",
    "type": "split",
    "children": [
      {
        "id": "5274640b7889050f",
        "type": "tabs",
        "children": [
          {
            "id": "f6a17273348d4dbc",
            "type": "leaf",
            "state": {
              "type": "backlink",
              "state": {
                "file": "typescript/Typescript 类型编程，从入门到念头通达.md",
                "collapseAll": false,
                "extraContext": false,
                "sortOrder": "alphabetical",
                "showSearch": false,
                "searchQuery": "",
                "backlinkCollapsed": false,
                "unlinkedCollapsed": true
              }
            }
          }
        ]
      }
    ],
    "direction": "horizontal",
    "width": 300,
    "collapsed": true
  },
  "active": "cce6c4baa23671cc",
  "lastOpenFiles": [
    "mock 数据接口相关.md",
    "vue3/admin.md",
    "谷歌翻译中国版停服！教你解决修复 Chrome 浏览器无法翻译网页的问题方法教程.md",
    "编译思想和设计模式/aop和ioc.md",
    "使用 Nx 进行有效的 React 开发/介绍.md",
    "vue3/高阶组件.md",
    "CSS/CSS网格的隐式网格和自动放置功能研究.md",
    "fromily 的配置.md",
    "组件问题/我的NPM最佳实践.md",
    "组件问题/前端基建.md"
  ]
}